hw/src/periph/prescaler/tim.sv

module div_clk (
input logic clk,     // Входной тактовый сигнал
input logic rst,    // Сигнал сброса
input logic[31:0] prescaler, // Коэффициент деления
output logic clk_pre // Выходной деленный тактовый сигнал
);

  logic[31:0] counter = 0;

	always @(posedge clk or posedge rst)
		if (rst) begin
			counter <= 0;
			clk_pre <= 0;
		end
		else begin
			if ((prescaler - 1) == counter) begin
				clk_pre <= ~clk_pre;
				counter <= 0;
			end
			else counter <= counter + 1;
		end

endmodule

hw/src/periph/prescaler/tb_tim.sv

module tb_tim;

    //localparam clk_mhz = 1,
    //------------------------------------------------------------------------
    logic       clk;
    logic       rst;
    logic divided_clk;
    logic[31:0] presc;
    //------------------------------------------------------------------------
    // Экземпляр тестируемого модуля
    div_clk div_tim 
    (
        .clk      ( clk ),
        .rst      ( rst ),
        .prescaler(presc),
        .clk_pre  (divided_clk)     
    );

    //------------------------------------------------------------------------
    // Генерация тактового сигнала
    initial
    begin
        clk = 1'b0;
        forever
            # 5 clk = ~ clk;
    end

    //------------------------------------------------------------------------
    // Инициализация
    initial
    begin
        rst <= 1'bx;
        repeat (2) @ (posedge clk);
        rst <= 1'b1;
        repeat (2) @ (posedge clk);
        rst <= 1'b0;
    end

  initial
  begin
    `ifdef __ICARUS__
      // Uncomment the following line
      // to generate a VCD file and analyze it using GTKwave or Surfer

      $dumpvars;
    `endif
    presc <= 16;
    #1000; // Длительность теста
    presc <= 8;
    #1000;
    $finish;
  end

endmodule

hw/src/periph/prescaler/dump.vcd
$date
	Mon Nov 25 12:26:54 2024
$end
$version
	Icarus Verilog
$end
$timescale
	1s
$end
$scope module tb_tim $end
$var wire 1 ! divided_clk $end
$var reg 1 " clk $end
$var reg 32 # presc [31:0] $end
$var reg 1 $ rst $end
$scope module div_tim $end
$var wire 1 " clk $end
$var wire 32 % prescaler [31:0] $end
$var wire 1 $ rst $end
$var reg 1 ! clk_pre $end
$var reg 32 & counter [31:0] $end
$upscope $end
$upscope $end
$enddefinitions $end
$comment Show the parameter values. $end
$dumpall
$end
#0
$dumpvars
b0 &
b10000 %
x$
b10000 #
0"
x!
$end
#5
b1 &
1"
#10
0"
#15
0!
b0 &
1$
1"
#20
0"
#25
1"
#30
0"
#35
0$
1"
#40
0"
#45
b1 &
1"
#50
0"
#55
b10 &
1"
#60
0"
#65
b11 &
1"
#70
0"
#75
b100 &
1"
#80
0"
#85
b101 &
1"
#90
0"
#95
b110 &
1"
#100
0"
#105
b111 &
1"
#110
0"
#115
b1000 &
1"
#120
0"
#125
b1001 &
1"
#130
0"
#135
b1010 &
1"
#140
0"
#145
b1011 &
1"
#150
0"
#155
b1100 &
1"
#160
0"
#165
b1101 &
1"
#170
0"
#175
b1110 &
1"
#180
0"
#185
b1111 &
1"
#190
0"
#195
b0 &
1!
1"
#200
0"
#205
b1 &
1"
#210
0"
#215
b10 &
1"
#220
0"
#225
b11 &
1"
#230
0"
#235
b100 &
1"
#240
0"
#245
b101 &
1"
#250
0"
#255
b110 &
1"
#260
0"
#265
b111 &
1"
#270
0"
#275
b1000 &
1"
#280
0"
#285
b1001 &
1"
#290
0"
#295
b1010 &
1"
#300
0"
#305
b1011 &
1"
#310
0"
#315
b1100 &
1"
#320
0"
#325
b1101 &
1"
#330
0"
#335
b1110 &
1"
#340
0"
#345
b1111 &
1"
#350
0"
#355
b0 &
0!
1"
#360
0"
#365
b1 &
1"
#370
0"
#375
b10 &
1"
#380
0"
#385
b11 &
1"
#390
0"
#395
b100 &
1"
#400
0"
#405
b101 &
1"
#410
0"
#415
b110 &
1"
#420
0"
#425
b111 &
1"
#430
0"
#435
b1000 &
1"
#440
0"
#445
b1001 &
1"
#450
0"
#455
b1010 &
1"
#460
0"
#465
b1011 &
1"
#470
0"
#475
b1100 &
1"
#480
0"
#485
b1101 &
1"
#490
0"
#495
b1110 &
1"
#500
0"
#505
b1111 &
1"
#510
0"
#515
b0 &
1!
1"
#520
0"
#525
b1 &
1"
#530
0"
#535
b10 &
1"
#540
0"
#545
b11 &
1"
#550
0"
#555
b100 &
1"
#560
0"
#565
b101 &
1"
#570
0"
#575
b110 &
1"
#580
0"
#585
b111 &
1"
#590
0"
#595
b1000 &
1"
#600
0"
#605
b1001 &
1"
#610
0"
#615
b1010 &
1"
#620
0"
#625
b1011 &
1"
#630
0"
#635
b1100 &
1"
#640
0"
#645
b1101 &
1"
#650
0"
#655
b1110 &
1"
#660
0"
#665
b1111 &
1"
#670
0"
#675
b0 &
0!
1"
#680
0"
#685
b1 &
1"
#690
0"
#695
b10 &
1"
#700
0"
#705
b11 &
1"
#710
0"
#715
b100 &
1"
#720
0"
#725
b101 &
1"
#730
0"
#735
b110 &
1"
#740
0"
#745
b111 &
1"
#750
0"
#755
b1000 &
1"
#760
0"
#765
b1001 &
1"
#770
0"
#775
b1010 &
1"
#780
0"
#785
b1011 &
1"
#790
0"
#795
b1100 &
1"
#800
0"
#805
b1101 &
1"
#810
0"
#815
b1110 &
1"
#820
0"
#825
b1111 &
1"
#830
0"
#835
b0 &
1!
1"
#840
0"
#845
b1 &
1"
#850
0"
#855
b10 &
1"
#860
0"
#865
b11 &
1"
#870
0"
#875
b100 &
1"
#880
0"
#885
b101 &
1"
#890
0"
#895
b110 &
1"
#900
0"
#905
b111 &
1"
#910
0"
#915
b1000 &
1"
#920
0"
#925
b1001 &
1"
#930
0"
#935
b1010 &
1"
#940
0"
#945
b1011 &
1"
#950
0"
#955
b1100 &
1"
#960
0"
#965
b1101 &
1"
#970
0"
#975
b1110 &
1"
#980
0"
#985
b1111 &
1"
#990
0"
#995
b0 &
0!
1"
#1000
b1000 #
b1000 %
0"
#1005
b1 &
1"
#1010
0"
#1015
b10 &
1"
#1020
0"
#1025
b11 &
1"
#1030
0"
#1035
b100 &
1"
#1040
0"
#1045
b101 &
1"
#1050
0"
#1055
b110 &
1"
#1060
0"
#1065
b111 &
1"
#1070
0"
#1075
b0 &
1!
1"
#1080
0"
#1085
b1 &
1"
#1090
0"
#1095
b10 &
1"
#1100
0"
#1105
b11 &
1"
#1110
0"
#1115
b100 &
1"
#1120
0"
#1125
b101 &
1"
#1130
0"
#1135
b110 &
1"
#1140
0"
#1145
b111 &
1"
#1150
0"
#1155
b0 &
0!
1"
#1160
0"
#1165
b1 &
1"
#1170
0"
#1175
b10 &
1"
#1180
0"
#1185
b11 &
1"
#1190
0"
#1195
b100 &
1"
#1200
0"
#1205
b101 &
1"
#1210
0"
#1215
b110 &
1"
#1220
0"
#1225
b111 &
1"
#1230
0"
#1235
b0 &
1!
1"
#1240
0"
#1245
b1 &
1"
#1250
0"
#1255
b10 &
1"
#1260
0"
#1265
b11 &
1"
#1270
0"
#1275
b100 &
1"
#1280
0"
#1285
b101 &
1"
#1290
0"
#1295
b110 &
1"
#1300
0"
#1305
b111 &
1"
#1310
0"
#1315
b0 &
0!
1"
#1320
0"
#1325
b1 &
1"
#1330
0"
#1335
b10 &
1"
#1340
0"
#1345
b11 &
1"
#1350
0"
#1355
b100 &
1"
#1360
0"
#1365
b101 &
1"
#1370
0"
#1375
b110 &
1"
#1380
0"
#1385
b111 &
1"
#1390
0"
#1395
b0 &
1!
1"
#1400
0"
#1405
b1 &
1"
#1410
0"
#1415
b10 &
1"
#1420
0"
#1425
b11 &
1"
#1430
0"
#1435
b100 &
1"
#1440
0"
#1445
b101 &
1"
#1450
0"
#1455
b110 &
1"
#1460
0"
#1465
b111 &
1"
#1470
0"
#1475
b0 &
0!
1"
#1480
0"
#1485
b1 &
1"
#1490
0"
#1495
b10 &
1"
#1500
0"
#1505
b11 &
1"
#1510
0"
#1515
b100 &
1"
#1520
0"
#1525
b101 &
1"
#1530
0"
#1535
b110 &
1"
#1540
0"
#1545
b111 &
1"
#1550
0"
#1555
b0 &
1!
1"
#1560
0"
#1565
b1 &
1"
#1570
0"
#1575
b10 &
1"
#1580
0"
#1585
b11 &
1"
#1590
0"
#1595
b100 &
1"
#1600
0"
#1605
b101 &
1"
#1610
0"
#1615
b110 &
1"
#1620
0"
#1625
b111 &
1"
#1630
0"
#1635
b0 &
0!
1"
#1640
0"
#1645
b1 &
1"
#1650
0"
#1655
b10 &
1"
#1660
0"
#1665
b11 &
1"
#1670
0"
#1675
b100 &
1"
#1680
0"
#1685
b101 &
1"
#1690
0"
#1695
b110 &
1"
#1700
0"
#1705
b111 &
1"
#1710
0"
#1715
b0 &
1!
1"
#1720
0"
#1725
b1 &
1"
#1730
0"
#1735
b10 &
1"
#1740
0"
#1745
b11 &
1"
#1750
0"
#1755
b100 &
1"
#1760
0"
#1765
b101 &
1"
#1770
0"
#1775
b110 &
1"
#1780
0"
#1785
b111 &
1"
#1790
0"
#1795
b0 &
0!
1"
#1800
0"
#1805
b1 &
1"
#1810
0"
#1815
b10 &
1"
#1820
0"
#1825
b11 &
1"
#1830
0"
#1835
b100 &
1"
#1840
0"
#1845
b101 &
1"
#1850
0"
#1855
b110 &
1"
#1860
0"
#1865
b111 &
1"
#1870
0"
#1875
b0 &
1!
1"
#1880
0"
#1885
b1 &
1"
#1890
0"
#1895
b10 &
1"
#1900
0"
#1905
b11 &
1"
#1910
0"
#1915
b100 &
1"
#1920
0"
#1925
b101 &
1"
#1930
0"
#1935
b110 &
1"
#1940
0"
#1945
b111 &
1"
#1950
0"
#1955
b0 &
0!
1"
#1960
0"
#1965
b1 &
1"
#1970
0"
#1975
b10 &
1"
#1980
0"
#1985
b11 &
1"
#1990
0"
#1995
b100 &
1"
