hw/src/periph/prescaler/tim.sv

module div_clk (
input logic clk,     // Входной тактовый сигнал
input logic rst,    // Сигнал сброса
input logic[15:0] prescaler, // Коэффициент деления
output logic clk_pre // Выходной деленный тактовый сигнал
);

   logic[15:0] counter = 0;

	always @(posedge clk or posedge rst)
		if (rst) counter <= 0;
		else begin
			if (prescaler == counter) counter <= 0;
			else counter <= counter + 1;
		end

	assign clk_pre = (counter == prescaler);

endmodule


module tim (
	input logic clk,
	input logic rst,
	input logic[15:0] prescaler,
	input logic[1:0] counter_mode,
	input logic[15:0] counter_period,
	input logic[15:0] pulse,
   input logic auto_reload_preload,

	output logic out_p_1,
	output logic out_n_1,
	output logic[15:0] out_counter
);

	logic[15:0] counter_tim = 0;
   logic[15:0] counter_period_tim = 0; // теневой(основной) регистр переполнени
	logic enable;

   div_clk div_tim 
    (
        .clk      ( clk ),
        .rst      ( rst ),
        .prescaler( prescaler ),
        .clk_pre  ( enable )     
    );
   
   logic load;                    //переполнение  
   logic direction;               // 0 - вверх, 1 - вниз
 
   always_ff @(posedge clk or posedge rst) begin
      if (rst) begin
         counter_tim <= 0;
         direction <= 0; // Начинаем с счета ввер
         counter_period_tim <= counter_period;
      end 
      else if (enable) begin
         if(~auto_reload_preload) counter_period_tim <= counter_period;
         else if(load) counter_period_tim <= counter_period;
         case (counter_mode)
            2'b00: begin // Счет вверх
               if (load) counter_tim <= 0;
               else counter_tim <= counter_tim + 1;
            end
            2'b01: begin // Счет вниз
               if (load) counter_tim <= counter_period_tim;
               else counter_tim <= counter_tim - 1;
            end
            2'b10: begin // Счет вверх-вниз
               if (direction == 0) begin // Счет вверх
                  if (counter_tim == counter_period_tim) begin
                     direction <= 1; // Меняем направление на вниз
                     counter_tim <= counter_tim - 1;
                  end 
                  else counter_tim <= counter_tim + 1;
               end
               else begin // Счет вниз
                  if (counter_tim == 0) begin
                     direction <= 0; // Меняем направление на вверх
                     counter_tim <= counter_tim + 1;
                  end 
                  else counter_tim <= counter_tim - 1;
               end
            end
         endcase
      end
   end

assign load = (counter_mode == 2'b00 && counter_tim == counter_period_tim) ||
              (counter_mode == 2'b01 && counter_tim == 0);

assign out_counter = counter_tim;
assign out_n_1 = counter_tim >= pulse;
assign out_p_1 = ~out_n_1;

endmodule

hw/src/periph/prescaler/tb_tim.sv

module tb_tim;

    //------------------------------------------------------------------------
    logic       clk;
    logic       rst;
    logic       enable;
    logic[15:0] prescaler;
    logic       auto_reload_preload;

    logic[1:0]  counter_mode;
    logic[15:0] counter_period;
    logic[15:0] pulse;
    logic out_1;
    logic out_2;
    //------------------------------------------------------------------------
    // Экземпляр тестируемого модуля
/*    
    div_clk div_clk 
    (
        .clk      ( clk ),
        .rst      ( rst ),
        .prescaler(prescaler),
        .clk_pre  (enable)     
    );
*/
    tim tim
    (
      .clk(clk),
      .rst(rst),
      .prescaler(prescaler),
      .counter_mode(counter_mode),
      .counter_period(counter_period),
      .pulse(pulse),
      .auto_reload_preload(auto_reload_preload),
      .out_p_1(out_1),
      .out_n_1(out_2)
    );

    //------------------------------------------------------------------------
    // Генерация тактового сигнала
    initial
    begin
        clk = 1'b0;
        forever
            # 5 clk = ~ clk;
    end

    //------------------------------------------------------------------------
    // Инициализация
    initial
    begin
        rst <= 1'bx;
        repeat (2) @ (posedge clk);
        rst <= 1'b1;
        repeat (2) @ (posedge clk);
        rst <= 1'b0;
    end

  initial
  begin
    `ifdef __ICARUS__
      // Uncomment the following line
      // to generate a VCD file and analyze it using GTKwave or Surfer

      $dumpvars;
    `endif
    prescaler <= 2;

    auto_reload_preload <= 0;
    counter_mode <= 2'b00;
    counter_period <= 10;
    pulse <= 5;
    #1000; // Длительность теста
    rst <= 1'b1;
    counter_mode <= 2'b01;
    #5
    rst <= 1'b0;
    #1000
    rst <= 1'b1;
    counter_mode <= 2'b10;
    auto_reload_preload <= 0;
    #5
    rst <= 1'b0;
    #500
    counter_period <= 15;
    #500
    $finish;
  end

endmodule

hw/src/periph/prescaler/dump.vcd
$date
	Thu Nov 28 16:55:10 2024
$end
$version
	Icarus Verilog
$end
$timescale
	1s
$end
$scope module tb_tim $end
$var wire 1 ! out_2 $end
$var wire 1 " out_1 $end
$var reg 1 # auto_reload_preload $end
$var reg 1 $ clk $end
$var reg 2 % counter_mode [1:0] $end
$var reg 16 & counter_period [15:0] $end
$var reg 16 ' prescaler [15:0] $end
$var reg 16 ( pulse [15:0] $end
$var reg 1 ) rst $end
$scope module tim $end
$var wire 1 # auto_reload_preload $end
$var wire 1 $ clk $end
$var wire 2 * counter_mode [1:0] $end
$var wire 16 + counter_period [15:0] $end
$var wire 1 , load $end
$var wire 16 - out_counter [15:0] $end
$var wire 1 " out_p_1 $end
$var wire 16 . prescaler [15:0] $end
$var wire 16 / pulse [15:0] $end
$var wire 1 ) rst $end
$var wire 1 ! out_n_1 $end
$var wire 1 0 enable $end
$var reg 16 1 counter_period_tim [15:0] $end
$var reg 16 2 counter_tim [15:0] $end
$var reg 1 3 direction $end
$scope module div_tim $end
$var wire 1 $ clk $end
$var wire 16 4 prescaler [15:0] $end
$var wire 1 ) rst $end
$var wire 1 0 clk_pre $end
$var reg 16 5 counter [15:0] $end
$upscope $end
$upscope $end
$upscope $end
$enddefinitions $end
$comment Show the parameter values. $end
$dumpall
$end
#0
$dumpvars
b0 5
b10 4
x3
b0 2
b0 1
00
b101 /
b10 .
b0 -
1,
b1010 +
b0 *
x)
b101 (
b10 '
b1010 &
b0 %
0$
0#
1"
0!
$end
#5
b1 5
1$
#10
0$
#15
0,
b1010 1
03
00
b0 5
1)
1$
#20
0$
#25
1$
#30
0$
#35
0)
1$
#40
0$
#45
b1 5
1$
#50
0$
#55
10
b10 5
1$
#60
0$
#65
b1 -
b1 2
00
b0 5
1$
#70
0$
#75
b1 5
1$
#80
0$
#85
10
b10 5
1$
#90
0$
#95
00
b0 5
b10 -
b10 2
1$
#100
0$
#105
b1 5
1$
#110
0$
#115
10
b10 5
1$
#120
0$
#125
b11 -
b11 2
00
b0 5
1$
#130
0$
#135
b1 5
1$
#140
0$
#145
10
b10 5
1$
#150
0$
#155
00
b0 5
b100 -
b100 2
1$
#160
0$
#165
b1 5
1$
#170
0$
#175
10
b10 5
1$
#180
0$
#185
0"
1!
b101 -
b101 2
00
b0 5
1$
#190
0$
#195
b1 5
1$
#200
0$
#205
10
b10 5
1$
#210
0$
#215
00
b0 5
b110 -
b110 2
1$
#220
0$
#225
b1 5
1$
#230
0$
#235
10
b10 5
1$
#240
0$
#245
b111 -
b111 2
00
b0 5
1$
#250
0$
#255
b1 5
1$
#260
0$
#265
10
b10 5
1$
#270
0$
#275
00
b0 5
b1000 -
b1000 2
1$
#280
0$
#285
b1 5
1$
#290
0$
#295
10
b10 5
1$
#300
0$
#305
b1001 -
b1001 2
00
b0 5
1$
#310
0$
#315
b1 5
1$
#320
0$
#325
10
b10 5
1$
#330
0$
#335
1,
00
b0 5
b1010 -
b1010 2
1$
#340
0$
#345
b1 5
1$
#350
0$
#355
10
b10 5
1$
#360
0$
#365
0,
1"
0!
b0 -
b0 2
00
b0 5
1$
#370
0$
#375
b1 5
1$
#380
0$
#385
10
b10 5
1$
#390
0$
#395
00
b0 5
b1 -
b1 2
1$
#400
0$
#405
b1 5
1$
#410
0$
#415
10
b10 5
1$
#420
0$
#425
b10 -
b10 2
00
b0 5
1$
#430
0$
#435
b1 5
1$
#440
0$
#445
10
b10 5
1$
#450
0$
#455
00
b0 5
b11 -
b11 2
1$
#460
0$
#465
b1 5
1$
#470
0$
#475
10
b10 5
1$
#480
0$
#485
b100 -
b100 2
00
b0 5
1$
#490
0$
#495
b1 5
1$
#500
0$
#505
10
b10 5
1$
#510
0$
#515
0"
00
b0 5
1!
b101 -
b101 2
1$
#520
0$
#525
b1 5
1$
#530
0$
#535
10
b10 5
1$
#540
0$
#545
b110 -
b110 2
00
b0 5
1$
#550
0$
#555
b1 5
1$
#560
0$
#565
10
b10 5
1$
#570
0$
#575
00
b0 5
b111 -
b111 2
1$
#580
0$
#585
b1 5
1$
#590
0$
#595
10
b10 5
1$
#600
0$
#605
b1000 -
b1000 2
00
b0 5
1$
#610
0$
#615
b1 5
1$
#620
0$
#625
10
b10 5
1$
#630
0$
#635
00
b0 5
b1001 -
b1001 2
1$
#640
0$
#645
b1 5
1$
#650
0$
#655
10
b10 5
1$
#660
0$
#665
1,
b1010 -
b1010 2
00
b0 5
1$
#670
0$
#675
b1 5
1$
#680
0$
#685
10
b10 5
1$
#690
0$
#695
0,
1"
00
b0 5
0!
b0 -
b0 2
1$
#700
0$
#705
b1 5
1$
#710
0$
#715
10
b10 5
1$
#720
0$
#725
b1 -
b1 2
00
b0 5
1$
#730
0$
#735
b1 5
1$
#740
0$
#745
10
b10 5
1$
#750
0$
#755
00
b0 5
b10 -
b10 2
1$
#760
0$
#765
b1 5
1$
#770
0$
#775
10
b10 5
1$
#780
0$
#785
b11 -
b11 2
00
b0 5
1$
#790
0$
#795
b1 5
1$
#800
0$
#805
10
b10 5
1$
#810
0$
#815
00
b0 5
b100 -
b100 2
1$
#820
0$
#825
b1 5
1$
#830
0$
#835
10
b10 5
1$
#840
0$
#845
0"
1!
b101 -
b101 2
00
b0 5
1$
#850
0$
#855
b1 5
1$
#860
0$
#865
10
b10 5
1$
#870
0$
#875
00
b0 5
b110 -
b110 2
1$
#880
0$
#885
b1 5
1$
#890
0$
#895
10
b10 5
1$
#900
0$
#905
b111 -
b111 2
00
b0 5
1$
#910
0$
#915
b1 5
1$
#920
0$
#925
10
b10 5
1$
#930
0$
#935
00
b0 5
b1000 -
b1000 2
1$
#940
0$
#945
b1 5
1$
#950
0$
#955
10
b10 5
1$
#960
0$
#965
b1001 -
b1001 2
00
b0 5
1$
#970
0$
#975
b1 5
1$
#980
0$
#985
10
b10 5
1$
#990
0$
#995
1,
00
b0 5
b1010 -
b1010 2
1$
#1000
1"
0!
b0 -
b0 2
1,
b1 %
b1 *
1)
0$
#1005
0)
1$
#1010
0$
#1015
b1 5
1$
#1020
0$
#1025
10
b10 5
1$
#1030
0$
#1035
0,
0"
1!
b1010 -
b1010 2
00
b0 5
1$
#1040
0$
#1045
b1 5
1$
#1050
0$
#1055
10
b10 5
1$
#1060
0$
#1065
00
b0 5
b1001 -
b1001 2
1$
#1070
0$
#1075
b1 5
1$
#1080
0$
#1085
10
b10 5
1$
#1090
0$
#1095
b1000 -
b1000 2
00
b0 5
1$
#1100
0$
#1105
b1 5
1$
#1110
0$
#1115
10
b10 5
1$
#1120
0$
#1125
00
b0 5
b111 -
b111 2
1$
#1130
0$
#1135
b1 5
1$
#1140
0$
#1145
10
b10 5
1$
#1150
0$
#1155
b110 -
b110 2
00
b0 5
1$
#1160
0$
#1165
b1 5
1$
#1170
0$
#1175
10
b10 5
1$
#1180
0$
#1185
00
b0 5
b101 -
b101 2
1$
#1190
0$
#1195
b1 5
1$
#1200
0$
#1205
10
b10 5
1$
#1210
0$
#1215
1"
0!
b100 -
b100 2
00
b0 5
1$
#1220
0$
#1225
b1 5
1$
#1230
0$
#1235
10
b10 5
1$
#1240
0$
#1245
00
b0 5
b11 -
b11 2
1$
#1250
0$
#1255
b1 5
1$
#1260
0$
#1265
10
b10 5
1$
#1270
0$
#1275
b10 -
b10 2
00
b0 5
1$
#1280
0$
#1285
b1 5
1$
#1290
0$
#1295
10
b10 5
1$
#1300
0$
#1305
00
b0 5
b1 -
b1 2
1$
#1310
0$
#1315
b1 5
1$
#1320
0$
#1325
10
b10 5
1$
#1330
0$
#1335
1,
b0 -
b0 2
00
b0 5
1$
#1340
0$
#1345
b1 5
1$
#1350
0$
#1355
10
b10 5
1$
#1360
0$
#1365
0,
0"
00
b0 5
1!
b1010 -
b1010 2
1$
#1370
0$
#1375
b1 5
1$
#1380
0$
#1385
10
b10 5
1$
#1390
0$
#1395
b1001 -
b1001 2
00
b0 5
1$
#1400
0$
#1405
b1 5
1$
#1410
0$
#1415
10
b10 5
1$
#1420
0$
#1425
00
b0 5
b1000 -
b1000 2
1$
#1430
0$
#1435
b1 5
1$
#1440
0$
#1445
10
b10 5
1$
#1450
0$
#1455
b111 -
b111 2
00
b0 5
1$
#1460
0$
#1465
b1 5
1$
#1470
0$
#1475
10
b10 5
1$
#1480
0$
#1485
00
b0 5
b110 -
b110 2
1$
#1490
0$
#1495
b1 5
1$
#1500
0$
#1505
10
b10 5
1$
#1510
0$
#1515
b101 -
b101 2
00
b0 5
1$
#1520
0$
#1525
b1 5
1$
#1530
0$
#1535
10
b10 5
1$
#1540
0$
#1545
1"
00
b0 5
0!
b100 -
b100 2
1$
#1550
0$
#1555
b1 5
1$
#1560
0$
#1565
10
b10 5
1$
#1570
0$
#1575
b11 -
b11 2
00
b0 5
1$
#1580
0$
#1585
b1 5
1$
#1590
0$
#1595
10
b10 5
1$
#1600
0$
#1605
00
b0 5
b10 -
b10 2
1$
#1610
0$
#1615
b1 5
1$
#1620
0$
#1625
10
b10 5
1$
#1630
0$
#1635
b1 -
b1 2
00
b0 5
1$
#1640
0$
#1645
b1 5
1$
#1650
0$
#1655
10
b10 5
1$
#1660
0$
#1665
1,
00
b0 5
b0 -
b0 2
1$
#1670
0$
#1675
b1 5
1$
#1680
0$
#1685
10
b10 5
1$
#1690
0$
#1695
0,
0"
1!
b1010 -
b1010 2
00
b0 5
1$
#1700
0$
#1705
b1 5
1$
#1710
0$
#1715
10
b10 5
1$
#1720
0$
#1725
00
b0 5
b1001 -
b1001 2
1$
#1730
0$
#1735
b1 5
1$
#1740
0$
#1745
10
b10 5
1$
#1750
0$
#1755
b1000 -
b1000 2
00
b0 5
1$
#1760
0$
#1765
b1 5
1$
#1770
0$
#1775
10
b10 5
1$
#1780
0$
#1785
00
b0 5
b111 -
b111 2
1$
#1790
0$
#1795
b1 5
1$
#1800
0$
#1805
10
b10 5
1$
#1810
0$
#1815
b110 -
b110 2
00
b0 5
1$
#1820
0$
#1825
b1 5
1$
#1830
0$
#1835
10
b10 5
1$
#1840
0$
#1845
00
b0 5
b101 -
b101 2
1$
#1850
0$
#1855
b1 5
1$
#1860
0$
#1865
10
b10 5
1$
#1870
0$
#1875
1"
0!
b100 -
b100 2
00
b0 5
1$
#1880
0$
#1885
b1 5
1$
#1890
0$
#1895
10
b10 5
1$
#1900
0$
#1905
00
b0 5
b11 -
b11 2
1$
#1910
0$
#1915
b1 5
1$
#1920
0$
#1925
10
b10 5
1$
#1930
0$
#1935
b10 -
b10 2
00
b0 5
1$
#1940
0$
#1945
b1 5
1$
#1950
0$
#1955
10
b10 5
1$
#1960
0$
#1965
00
b0 5
b1 -
b1 2
1$
#1970
0$
#1975
b1 5
1$
#1980
0$
#1985
10
b10 5
1$
#1990
0$
#1995
1,
b0 -
b0 2
00
b0 5
1$
#2000
0$
#2005
0,
b0 5
b10 %
b10 *
1)
1$
#2010
0)
0$
#2015
b1 5
1$
#2020
0$
#2025
10
b10 5
1$
#2030
0$
#2035
00
b0 5
b1 -
b1 2
1$
#2040
0$
#2045
b1 5
1$
#2050
0$
#2055
10
b10 5
1$
#2060
0$
#2065
b10 -
b10 2
00
b0 5
1$
#2070
0$
#2075
b1 5
1$
#2080
0$
#2085
10
b10 5
1$
#2090
0$
#2095
00
b0 5
b11 -
b11 2
1$
#2100
0$
#2105
b1 5
1$
#2110
0$
#2115
10
b10 5
1$
#2120
0$
#2125
b100 -
b100 2
00
b0 5
1$
#2130
0$
#2135
b1 5
1$
#2140
0$
#2145
10
b10 5
1$
#2150
0$
#2155
0"
00
b0 5
1!
b101 -
b101 2
1$
#2160
0$
#2165
b1 5
1$
#2170
0$
#2175
10
b10 5
1$
#2180
0$
#2185
b110 -
b110 2
00
b0 5
1$
#2190
0$
#2195
b1 5
1$
#2200
0$
#2205
10
b10 5
1$
#2210
0$
#2215
00
b0 5
b111 -
b111 2
1$
#2220
0$
#2225
b1 5
1$
#2230
0$
#2235
10
b10 5
1$
#2240
0$
#2245
b1000 -
b1000 2
00
b0 5
1$
#2250
0$
#2255
b1 5
1$
#2260
0$
#2265
10
b10 5
1$
#2270
0$
#2275
00
b0 5
b1001 -
b1001 2
1$
#2280
0$
#2285
b1 5
1$
#2290
0$
#2295
10
b10 5
1$
#2300
0$
#2305
b1010 -
b1010 2
00
b0 5
1$
#2310
0$
#2315
b1 5
1$
#2320
0$
#2325
10
b10 5
1$
#2330
0$
#2335
00
b0 5
b1001 -
b1001 2
13
1$
#2340
0$
#2345
b1 5
1$
#2350
0$
#2355
10
b10 5
1$
#2360
0$
#2365
b1000 -
b1000 2
00
b0 5
1$
#2370
0$
#2375
b1 5
1$
#2380
0$
#2385
10
b10 5
1$
#2390
0$
#2395
00
b0 5
b111 -
b111 2
1$
#2400
0$
#2405
b1 5
1$
#2410
0$
#2415
10
b10 5
1$
#2420
0$
#2425
b110 -
b110 2
00
b0 5
1$
#2430
0$
#2435
b1 5
1$
#2440
0$
#2445
10
b10 5
1$
#2450
0$
#2455
00
b0 5
b101 -
b101 2
1$
#2460
0$
#2465
b1 5
1$
#2470
0$
#2475
10
b10 5
1$
#2480
0$
#2485
1"
0!
b100 -
b100 2
00
b0 5
1$
#2490
0$
#2495
b1 5
1$
#2500
0$
#2505
10
b10 5
1$
#2510
b1111 &
b1111 +
0$
#2515
00
b0 5
b11 -
b11 2
b1111 1
1$
#2520
0$
#2525
b1 5
1$
#2530
0$
#2535
10
b10 5
1$
#2540
0$
#2545
b10 -
b10 2
00
b0 5
1$
#2550
0$
#2555
b1 5
1$
#2560
0$
#2565
10
b10 5
1$
#2570
0$
#2575
00
b0 5
b1 -
b1 2
1$
#2580
0$
#2585
b1 5
1$
#2590
0$
#2595
10
b10 5
1$
#2600
0$
#2605
b0 -
b0 2
00
b0 5
1$
#2610
0$
#2615
b1 5
1$
#2620
0$
#2625
10
b10 5
1$
#2630
0$
#2635
00
b0 5
b1 -
b1 2
03
1$
#2640
0$
#2645
b1 5
1$
#2650
0$
#2655
10
b10 5
1$
#2660
0$
#2665
b10 -
b10 2
00
b0 5
1$
#2670
0$
#2675
b1 5
1$
#2680
0$
#2685
10
b10 5
1$
#2690
0$
#2695
00
b0 5
b11 -
b11 2
1$
#2700
0$
#2705
b1 5
1$
#2710
0$
#2715
10
b10 5
1$
#2720
0$
#2725
b100 -
b100 2
00
b0 5
1$
#2730
0$
#2735
b1 5
1$
#2740
0$
#2745
10
b10 5
1$
#2750
0$
#2755
0"
00
b0 5
1!
b101 -
b101 2
1$
#2760
0$
#2765
b1 5
1$
#2770
0$
#2775
10
b10 5
1$
#2780
0$
#2785
b110 -
b110 2
00
b0 5
1$
#2790
0$
#2795
b1 5
1$
#2800
0$
#2805
10
b10 5
1$
#2810
0$
#2815
00
b0 5
b111 -
b111 2
1$
#2820
0$
#2825
b1 5
1$
#2830
0$
#2835
10
b10 5
1$
#2840
0$
#2845
b1000 -
b1000 2
00
b0 5
1$
#2850
0$
#2855
b1 5
1$
#2860
0$
#2865
10
b10 5
1$
#2870
0$
#2875
00
b0 5
b1001 -
b1001 2
1$
#2880
0$
#2885
b1 5
1$
#2890
0$
#2895
10
b10 5
1$
#2900
0$
#2905
b1010 -
b1010 2
00
b0 5
1$
#2910
0$
#2915
b1 5
1$
#2920
0$
#2925
10
b10 5
1$
#2930
0$
#2935
00
b0 5
b1011 -
b1011 2
1$
#2940
0$
#2945
b1 5
1$
#2950
0$
#2955
10
b10 5
1$
#2960
0$
#2965
b1100 -
b1100 2
00
b0 5
1$
#2970
0$
#2975
b1 5
1$
#2980
0$
#2985
10
b10 5
1$
#2990
0$
#2995
00
b0 5
b1101 -
b1101 2
1$
#3000
0$
#3005
b1 5
1$
