hw/src/periph/prescaler/tim.sv

module div_clk (
input logic clk,     // Входной тактовый сигнал
input logic rst,    // Сигнал сброса
input logic[15:0] prescaler, // Коэффициент деления
output logic clk_pre // Выходной деленный тактовый сигнал
);

  logic[15:0] counter = 0;

	always @(posedge clk or posedge rst)
		if (rst) begin
			counter <= 0;
		end
		else begin
			if (prescaler == counter) begin
				counter <= 0;
			end
			else counter <= counter + 1;
		end

	assign clk_pre = (counter == prescaler);

endmodule


module tim (
	input logic clk,
	input logic rst,
	input logic[15:0] prescaler,
	input logic[1:0] counter_mode,
	input logic[15:0] counter_period,
	input logic[15:0] pulse,

	output logic out_p_1,
	output logic out_n_1
);

	logic[15:0] counter_tim = 0;
	logic enable;

    div_clk div_tim 
    (
        .clk      ( clk ),
        .rst      ( rst ),
        .prescaler( prescaler ),
        .clk_pre  ( enable )     
    );

	always @(posedge clk or posedge rst)
		if (rst) begin
			counter_tim <= 0;
		end
		else if (enable) begin
			if(counter_mode == 0) begin
				if (counter_period == counter_tim) counter_tim <= 0;
				else counter_tim <= counter_tim + 1;
			end
		end

	assign out_p_1 = (counter_tim == counter_period);
	assign out_n_1 = ~out_p_1;

endmodule

hw/src/periph/prescaler/tb_tim.sv

module tb_tim;

    //------------------------------------------------------------------------
    logic       clk;
    logic       rst;
    logic       enable;
    logic[15:0] prescaler;

    logic[1:0]  counter_mode;
    logic[15:0] counter_period;
    logic[15:0] pulse;
    logic out_1;
    logic out_2;
    //------------------------------------------------------------------------
    // Экземпляр тестируемого модуля
/*    
    div_clk div_clk 
    (
        .clk      ( clk ),
        .rst      ( rst ),
        .prescaler(prescaler),
        .clk_pre  (enable)     
    );
*/
    tim tim
    (
      .clk(clk),
      .rst(rst),
      .prescaler(prescaler),
      .counter_mode(counter_mode),
      .counter_period(counter_period),
      .pulse(pulse),
      .out_p_1(out_1),
      .out_n_1(out_2)
    );

    //------------------------------------------------------------------------
    // Генерация тактового сигнала
    initial
    begin
        clk = 1'b0;
        forever
            # 5 clk = ~ clk;
    end

    //------------------------------------------------------------------------
    // Инициализация
    initial
    begin
        rst <= 1'bx;
        repeat (2) @ (posedge clk);
        rst <= 1'b1;
        repeat (2) @ (posedge clk);
        rst <= 1'b0;
    end

  initial
  begin
    `ifdef __ICARUS__
      // Uncomment the following line
      // to generate a VCD file and analyze it using GTKwave or Surfer

      $dumpvars;
    `endif
    counter_mode <= 0;
    counter_period <= 4;
    prescaler <= 3;
    #1000; // Длительность теста
    $finish;
  end

endmodule

hw/src/periph/prescaler/dump.vcd
$date
	Tue Nov 26 09:00:20 2024
$end
$version
	Icarus Verilog
$end
$timescale
	1s
$end
$scope module tb_tim $end
$var wire 1 ! out_2 $end
$var wire 1 " out_1 $end
$var reg 1 # clk $end
$var reg 2 $ counter_mode [1:0] $end
$var reg 16 % counter_period [15:0] $end
$var reg 16 & prescaler [15:0] $end
$var reg 16 ' pulse [15:0] $end
$var reg 1 ( rst $end
$scope module tim $end
$var wire 1 # clk $end
$var wire 2 ) counter_mode [1:0] $end
$var wire 16 * counter_period [15:0] $end
$var wire 1 ! out_n_1 $end
$var wire 16 + prescaler [15:0] $end
$var wire 16 , pulse [15:0] $end
$var wire 1 ( rst $end
$var wire 1 " out_p_1 $end
$var wire 1 - enable $end
$var reg 16 . counter_tim [15:0] $end
$scope module div_tim $end
$var wire 1 # clk $end
$var wire 16 / prescaler [15:0] $end
$var wire 1 ( rst $end
$var wire 1 - clk_pre $end
$var reg 16 0 counter [15:0] $end
$upscope $end
$upscope $end
$upscope $end
$enddefinitions $end
$comment Show the parameter values. $end
$dumpall
$end
#0
$dumpvars
b0 0
b11 /
b0 .
0-
bx ,
b11 +
b100 *
b0 )
x(
bx '
b11 &
b100 %
b0 $
0#
0"
1!
$end
#5
b1 0
1#
#10
0#
#15
b0 0
1(
1#
#20
0#
#25
1#
#30
0#
#35
0(
1#
#40
0#
#45
b1 0
1#
#50
0#
#55
b10 0
1#
#60
0#
#65
1-
b11 0
1#
#70
0#
#75
0-
b0 0
b1 .
1#
#80
0#
#85
b1 0
1#
#90
0#
#95
b10 0
1#
#100
0#
#105
1-
b11 0
1#
#110
0#
#115
0-
b0 0
b10 .
1#
#120
0#
#125
b1 0
1#
#130
0#
#135
b10 0
1#
#140
0#
#145
1-
b11 0
1#
#150
0#
#155
0-
b0 0
b11 .
1#
#160
0#
#165
b1 0
1#
#170
0#
#175
b10 0
1#
#180
0#
#185
1-
b11 0
1#
#190
0#
#195
0!
0-
b0 0
1"
b100 .
1#
#200
0#
#205
b1 0
1#
#210
0#
#215
b10 0
1#
#220
0#
#225
1-
b11 0
1#
#230
0#
#235
1!
0-
b0 0
0"
b0 .
1#
#240
0#
#245
b1 0
1#
#250
0#
#255
b10 0
1#
#260
0#
#265
1-
b11 0
1#
#270
0#
#275
0-
b0 0
b1 .
1#
#280
0#
#285
b1 0
1#
#290
0#
#295
b10 0
1#
#300
0#
#305
1-
b11 0
1#
#310
0#
#315
0-
b0 0
b10 .
1#
#320
0#
#325
b1 0
1#
#330
0#
#335
b10 0
1#
#340
0#
#345
1-
b11 0
1#
#350
0#
#355
0-
b0 0
b11 .
1#
#360
0#
#365
b1 0
1#
#370
0#
#375
b10 0
1#
#380
0#
#385
1-
b11 0
1#
#390
0#
#395
0!
0-
b0 0
1"
b100 .
1#
#400
0#
#405
b1 0
1#
#410
0#
#415
b10 0
1#
#420
0#
#425
1-
b11 0
1#
#430
0#
#435
1!
0-
b0 0
0"
b0 .
1#
#440
0#
#445
b1 0
1#
#450
0#
#455
b10 0
1#
#460
0#
#465
1-
b11 0
1#
#470
0#
#475
0-
b0 0
b1 .
1#
#480
0#
#485
b1 0
1#
#490
0#
#495
b10 0
1#
#500
0#
#505
1-
b11 0
1#
#510
0#
#515
0-
b0 0
b10 .
1#
#520
0#
#525
b1 0
1#
#530
0#
#535
b10 0
1#
#540
0#
#545
1-
b11 0
1#
#550
0#
#555
0-
b0 0
b11 .
1#
#560
0#
#565
b1 0
1#
#570
0#
#575
b10 0
1#
#580
0#
#585
1-
b11 0
1#
#590
0#
#595
0!
0-
b0 0
1"
b100 .
1#
#600
0#
#605
b1 0
1#
#610
0#
#615
b10 0
1#
#620
0#
#625
1-
b11 0
1#
#630
0#
#635
1!
0-
b0 0
0"
b0 .
1#
#640
0#
#645
b1 0
1#
#650
0#
#655
b10 0
1#
#660
0#
#665
1-
b11 0
1#
#670
0#
#675
0-
b0 0
b1 .
1#
#680
0#
#685
b1 0
1#
#690
0#
#695
b10 0
1#
#700
0#
#705
1-
b11 0
1#
#710
0#
#715
0-
b0 0
b10 .
1#
#720
0#
#725
b1 0
1#
#730
0#
#735
b10 0
1#
#740
0#
#745
1-
b11 0
1#
#750
0#
#755
0-
b0 0
b11 .
1#
#760
0#
#765
b1 0
1#
#770
0#
#775
b10 0
1#
#780
0#
#785
1-
b11 0
1#
#790
0#
#795
0!
0-
b0 0
1"
b100 .
1#
#800
0#
#805
b1 0
1#
#810
0#
#815
b10 0
1#
#820
0#
#825
1-
b11 0
1#
#830
0#
#835
1!
0-
b0 0
0"
b0 .
1#
#840
0#
#845
b1 0
1#
#850
0#
#855
b10 0
1#
#860
0#
#865
1-
b11 0
1#
#870
0#
#875
0-
b0 0
b1 .
1#
#880
0#
#885
b1 0
1#
#890
0#
#895
b10 0
1#
#900
0#
#905
1-
b11 0
1#
#910
0#
#915
0-
b0 0
b10 .
1#
#920
0#
#925
b1 0
1#
#930
0#
#935
b10 0
1#
#940
0#
#945
1-
b11 0
1#
#950
0#
#955
0-
b0 0
b11 .
1#
#960
0#
#965
b1 0
1#
#970
0#
#975
b10 0
1#
#980
0#
#985
1-
b11 0
1#
#990
0#
#995
0!
0-
b0 0
1"
b100 .
1#
